{
  "cut_carrot": {
    "audio_file": "dataset\\cut_carrot_split\\cut_carrot_night.m4a",
    "annotations": {
      "sound_recognition": {
        "caption": "Sound events detected: running water, dish clattering, hand movements, slight background noise.",
        "question": "What are the main sound sources in this audio?",
        "answer": "Water running, dishes, and hand movements"
      },
      "sound_counting": {
        "caption": "Countable sounds: 3 distinct water bursts, 5 dish clatters, multiple hand movements.",
        "question": [
          "How many times do you hear distinct water bursts?",
          "How many dish clatters are there?",
          "How many times do you hear distinct water bursts?",
          "How many dish clatters are there?",
          "How many times do you hear distinct water bursts?",
          "How many dish clatters are there?",
          "How many times do you hear distinct water bursts?",
          "How many dish clatters are there?"
        ],
        "answer": [
          "3 times",
          "5 times",
          "Multiple occurrences",
          "3 times",
          "5 times",
          "Multiple occurrences",
          "3 times",
          "5 times",
          "Multiple occurrences",
          "3 times",
          "5 times",
          "Multiple occurrences"
        ]
      },
      "sound_sequence": {
        "caption": "Sequence: Initial water sound, followed by dish movement, then clattering, ending with ambient sound.",
        "question": [
          "What sound occurs first?",
          "What happens after the water stops?",
          "What sound occurs first?",
          "What happens after the water stops?",
          "What sound occurs first?",
          "What happens after the water stops?",
          "What sound occurs first?",
          "What happens after the water stops?"
        ],
        "answer": [
          "Water running",
          "Dish movement begins",
          "Clattering sounds",
          "Ambient noise",
          "Water running",
          "Dish movement begins",
          "Clattering sounds",
          "Ambient noise"
        ]
      },
      "sound_spatial": {
        "caption": "Spatial audio: Water appears close, centered. Dish sounds seem to move across the stereo field.",
        "question": "Where does the main water sound appear to come from?",
        "answer": "Center position, close to the microphone"
      },
      "speech_recognition": {
        "caption": "No clear speech detected. Background ambient sound and environmental noise present.",
        "question": [
          "Is there speech in the audio?",
          "How many speakers can you identify?",
          "Is there speech in the audio?",
          "How many speakers can you identify?",
          "Is there speech in the audio?",
          "How many speakers can you identify?",
          "Is there speech in the audio?",
          "How many speakers can you identify?"
        ],
        "answer": [
          "No clear speech",
          "No speakers detected",
          "Only environmental sounds",
          "No clear speech",
          "No speakers detected",
          "Only environmental sounds",
          "No clear speech",
          "No speakers detected",
          "Only environmental sounds",
          "No clear speech",
          "No speakers detected",
          "Only environmental sounds"
        ]
      },
      "music_recognition": {
        "caption": "No music detected. Only natural environmental sounds and action-related audio.",
        "question": [
          "Is there music in the audio?",
          "What is the style of music?",
          "Is there music in the audio?",
          "What is the style of music?",
          "Is there music in the audio?",
          "What is the style of music?",
          "Is there music in the audio?",
          "What is the style of music?"
        ],
        "answer": [
          "No music detected",
          "Not applicable",
          "Only natural sounds",
          "No music detected",
          "Not applicable",
          "Only natural sounds",
          "No music detected",
          "Not applicable",
          "Only natural sounds",
          "No music detected",
          "Not applicable",
          "Only natural sounds"
        ]
      },
      "environmental_scene": {
        "caption": "Environment: Indoor kitchen or wash area. Sounds suggest water, dishes, and daily activity.",
        "question": [
          "What environment do the sounds suggest?",
          "What room is this likely?",
          "What environment do the sounds suggest?",
          "What room is this likely?",
          "What environment do the sounds suggest?",
          "What room is this likely?",
          "What environment do the sounds suggest?",
          "What room is this likely?"
        ],
        "answer": [
          "Kitchen or wash area",
          "Kitchen/bathroom",
          "Domestic indoor space",
          "Kitchen or wash area",
          "Kitchen/bathroom",
          "Domestic indoor space",
          "Kitchen or wash area",
          "Kitchen/bathroom",
          "Domestic indoor space",
          "Kitchen or wash area",
          "Kitchen/bathroom",
          "Domestic indoor space"
        ]
      },
      "audio_change": {
        "caption": "Changes detected: Sound starts with water, peaks with clattering, then quiets to ambient level.",
        "question": [
          "Does the audio get louder over time?",
          "What is the loudest event?",
          "Does the audio get louder over time?",
          "What is the loudest event?",
          "Does the audio get louder over time?",
          "What is the loudest event?",
          "Does the audio get louder over time?",
          "What is the loudest event?"
        ],
        "answer": [
          "Initially yes, then decreases",
          "Dish clattering",
          "Activity sounds",
          "Initially yes, then decreases",
          "Dish clattering",
          "Activity sounds",
          "Initially yes, then decreases",
          "Dish clattering",
          "Activity sounds",
          "Initially yes, then decreases",
          "Dish clattering",
          "Activity sounds"
        ]
      },
      "audio_visual_correspondence": {
        "caption": "Expected visual match: Water pouring, dish handling, hand movements. All consistent with typical kitchen activity.",
        "question": [
          "Could these sounds match a kitchen activity?",
          "What action is likely?",
          "Could these sounds match a kitchen activity?",
          "What action is likely?",
          "Could these sounds match a kitchen activity?",
          "What action is likely?",
          "Could these sounds match a kitchen activity?",
          "What action is likely?"
        ],
        "answer": [
          "Yes, strongly matches",
          "Washing dishes or hands",
          "Kitchen activity",
          "Yes, strongly matches",
          "Washing dishes or hands",
          "Kitchen activity",
          "Yes, strongly matches",
          "Washing dishes or hands",
          "Kitchen activity",
          "Yes, strongly matches",
          "Washing dishes or hands",
          "Kitchen activity"
        ]
      },
      "action_from_sound": {
        "caption": "Inferred actions: Water pouring or running, picking up dishes, putting items down, hand cleaning.",
        "question": [
          "What action is happening first?",
          "What objects are involved?",
          "What action is happening first?",
          "What objects are involved?",
          "What action is happening first?",
          "What objects are involved?",
          "What action is happening first?",
          "What objects are involved?"
        ],
        "answer": [
          "Water running",
          "Dishes and hands",
          "Water and objects",
          "Water running",
          "Dishes and hands",
          "Water and objects",
          "Water running",
          "Dishes and hands",
          "Water and objects",
          "Water running",
          "Dishes and hands",
          "Water and objects"
        ]
      }
    }
  },
  "wash_hands": {
    "audio_file": "dataset\\wash_hand_split\\wash_hands_night.m4a",
    "annotations": {
      "sound_recognition": {
        "caption": "Sound events detected: running water, dish clattering, hand movements, slight background noise.",
        "question": "What are the main sound sources in this audio?",
        "answer": "Water running, dishes, and hand movements"
      },
      "sound_counting": {
        "caption": "Countable sounds: 3 distinct water bursts, 5 dish clatters, multiple hand movements.",
        "question": [
          "How many times do you hear distinct water bursts?",
          "How many dish clatters are there?",
          "How many times do you hear distinct water bursts?",
          "How many dish clatters are there?",
          "How many times do you hear distinct water bursts?",
          "How many dish clatters are there?",
          "How many times do you hear distinct water bursts?",
          "How many dish clatters are there?"
        ],
        "answer": [
          "3 times",
          "5 times",
          "Multiple occurrences",
          "3 times",
          "5 times",
          "Multiple occurrences",
          "3 times",
          "5 times",
          "Multiple occurrences",
          "3 times",
          "5 times",
          "Multiple occurrences"
        ]
      },
      "sound_sequence": {
        "caption": "Sequence: Initial water sound, followed by dish movement, then clattering, ending with ambient sound.",
        "question": [
          "What sound occurs first?",
          "What happens after the water stops?",
          "What sound occurs first?",
          "What happens after the water stops?",
          "What sound occurs first?",
          "What happens after the water stops?",
          "What sound occurs first?",
          "What happens after the water stops?"
        ],
        "answer": [
          "Water running",
          "Dish movement begins",
          "Clattering sounds",
          "Ambient noise",
          "Water running",
          "Dish movement begins",
          "Clattering sounds",
          "Ambient noise"
        ]
      },
      "sound_spatial": {
        "caption": "Spatial audio: Water appears close, centered. Dish sounds seem to move across the stereo field.",
        "question": "Where does the main water sound appear to come from?",
        "answer": "Center position, close to the microphone"
      },
      "speech_recognition": {
        "caption": "No clear speech detected. Background ambient sound and environmental noise present.",
        "question": [
          "Is there speech in the audio?",
          "How many speakers can you identify?",
          "Is there speech in the audio?",
          "How many speakers can you identify?",
          "Is there speech in the audio?",
          "How many speakers can you identify?",
          "Is there speech in the audio?",
          "How many speakers can you identify?"
        ],
        "answer": [
          "No clear speech",
          "No speakers detected",
          "Only environmental sounds",
          "No clear speech",
          "No speakers detected",
          "Only environmental sounds",
          "No clear speech",
          "No speakers detected",
          "Only environmental sounds",
          "No clear speech",
          "No speakers detected",
          "Only environmental sounds"
        ]
      },
      "music_recognition": {
        "caption": "No music detected. Only natural environmental sounds and action-related audio.",
        "question": [
          "Is there music in the audio?",
          "What is the style of music?",
          "Is there music in the audio?",
          "What is the style of music?",
          "Is there music in the audio?",
          "What is the style of music?",
          "Is there music in the audio?",
          "What is the style of music?"
        ],
        "answer": [
          "No music detected",
          "Not applicable",
          "Only natural sounds",
          "No music detected",
          "Not applicable",
          "Only natural sounds",
          "No music detected",
          "Not applicable",
          "Only natural sounds",
          "No music detected",
          "Not applicable",
          "Only natural sounds"
        ]
      },
      "environmental_scene": {
        "caption": "Environment: Indoor kitchen or wash area. Sounds suggest water, dishes, and daily activity.",
        "question": [
          "What environment do the sounds suggest?",
          "What room is this likely?",
          "What environment do the sounds suggest?",
          "What room is this likely?",
          "What environment do the sounds suggest?",
          "What room is this likely?",
          "What environment do the sounds suggest?",
          "What room is this likely?"
        ],
        "answer": [
          "Kitchen or wash area",
          "Kitchen/bathroom",
          "Domestic indoor space",
          "Kitchen or wash area",
          "Kitchen/bathroom",
          "Domestic indoor space",
          "Kitchen or wash area",
          "Kitchen/bathroom",
          "Domestic indoor space",
          "Kitchen or wash area",
          "Kitchen/bathroom",
          "Domestic indoor space"
        ]
      },
      "audio_change": {
        "caption": "Changes detected: Sound starts with water, peaks with clattering, then quiets to ambient level.",
        "question": [
          "Does the audio get louder over time?",
          "What is the loudest event?",
          "Does the audio get louder over time?",
          "What is the loudest event?",
          "Does the audio get louder over time?",
          "What is the loudest event?",
          "Does the audio get louder over time?",
          "What is the loudest event?"
        ],
        "answer": [
          "Initially yes, then decreases",
          "Dish clattering",
          "Activity sounds",
          "Initially yes, then decreases",
          "Dish clattering",
          "Activity sounds",
          "Initially yes, then decreases",
          "Dish clattering",
          "Activity sounds",
          "Initially yes, then decreases",
          "Dish clattering",
          "Activity sounds"
        ]
      },
      "audio_visual_correspondence": {
        "caption": "Expected visual match: Water pouring, dish handling, hand movements. All consistent with typical kitchen activity.",
        "question": [
          "Could these sounds match a kitchen activity?",
          "What action is likely?",
          "Could these sounds match a kitchen activity?",
          "What action is likely?",
          "Could these sounds match a kitchen activity?",
          "What action is likely?",
          "Could these sounds match a kitchen activity?",
          "What action is likely?"
        ],
        "answer": [
          "Yes, strongly matches",
          "Washing dishes or hands",
          "Kitchen activity",
          "Yes, strongly matches",
          "Washing dishes or hands",
          "Kitchen activity",
          "Yes, strongly matches",
          "Washing dishes or hands",
          "Kitchen activity",
          "Yes, strongly matches",
          "Washing dishes or hands",
          "Kitchen activity"
        ]
      },
      "action_from_sound": {
        "caption": "Inferred actions: Water pouring or running, picking up dishes, putting items down, hand cleaning.",
        "question": [
          "What action is happening first?",
          "What objects are involved?",
          "What action is happening first?",
          "What objects are involved?",
          "What action is happening first?",
          "What objects are involved?",
          "What action is happening first?",
          "What objects are involved?"
        ],
        "answer": [
          "Water running",
          "Dishes and hands",
          "Water and objects",
          "Water running",
          "Dishes and hands",
          "Water and objects",
          "Water running",
          "Dishes and hands",
          "Water and objects",
          "Water running",
          "Dishes and hands",
          "Water and objects"
        ]
      }
    }
  }
}