{
  "dataset\\cut_carrot_split\\cut_carrot_day_seg_001": {
    "source_prefix": "cut_carrot_day",
    "side": "day",
    "segment": {
      "segment_id": "cut_carrot_day_seg_001",
      "task_label": "peeling carrot",
      "start_seconds": 0.0,
      "end_seconds": 45.0,
      "start_timestamp": "00:00:00.000",
      "end_timestamp": "00:00:45.000"
    },
    "source_file": "dataset\\cut_carrot_split\\cut_carrot_day_ir.mp4",
    "annotations": {
      "object_recognition": {
        "caption": "",
        "question": "",
        "answer": ""
      },
      "spatial_reasoning": {
        "caption": "",
        "question": "",
        "answer": ""
      },
      "text_recognition": {
        "caption": "",
        "question": "",
        "answer": ""
      },
      "scene_sequence": {
        "caption": "",
        "question": "",
        "answer": ""
      },
      "light_recongnition": {
        "caption": "",
        "question": "",
        "answer": ""
      },
      "light_change": {
        "caption": "",
        "question": "",
        "answer": ""
      },
      "counting": {
        "caption": "",
        "question": "",
        "answer": ""
      },
      "dynamic_counting": {
        "caption": "",
        "question": "",
        "answer": ""
      },
      "non_common": {
        "caption": "",
        "question": "",
        "answer": ""
      },
      "navigation": {
        "caption": "",
        "question": "",
        "answer": ""
      },
      "dynamic_recognition": {
        "caption": "",
        "question": "",
        "answer": ""
      },
      "action": {
        "caption": "",
        "question": "",
        "answer": ""
      }
    }
  },
  "dataset\\cut_carrot_split\\cut_carrot_day_seg_002": {
    "source_prefix": "cut_carrot_day",
    "side": "day",
    "segment": {
      "segment_id": "cut_carrot_day_seg_002",
      "task_label": "slicing carrot",
      "start_seconds": 45.0,
      "end_seconds": 185.0,
      "start_timestamp": "00:00:45.000",
      "end_timestamp": "00:03:05.000"
    },
    "source_file": "dataset\\cut_carrot_split\\cut_carrot_day_ir.mp4",
    "annotations": {
      "object_recognition": {
        "caption": "",
        "question": "",
        "answer": ""
      },
      "spatial_reasoning": {
        "caption": "",
        "question": "",
        "answer": ""
      },
      "text_recognition": {
        "caption": "",
        "question": "",
        "answer": ""
      },
      "scene_sequence": {
        "caption": "",
        "question": "",
        "answer": ""
      },
      "light_recongnition": {
        "caption": "",
        "question": "",
        "answer": ""
      },
      "light_change": {
        "caption": "",
        "question": "",
        "answer": ""
      },
      "counting": {
        "caption": "",
        "question": "",
        "answer": ""
      },
      "dynamic_counting": {
        "caption": "",
        "question": "",
        "answer": ""
      },
      "non_common": {
        "caption": "",
        "question": "",
        "answer": ""
      },
      "navigation": {
        "caption": "",
        "question": "",
        "answer": ""
      },
      "dynamic_recognition": {
        "caption": "",
        "question": "",
        "answer": ""
      },
      "action": {
        "caption": "",
        "question": "",
        "answer": ""
      }
    }
  },
  "dataset\\cut_carrot_split\\cut_carrot_night_seg_001": {
    "source_prefix": "cut_carrot_night",
    "side": "night",
    "segment": {
      "segment_id": "cut_carrot_night_seg_001",
      "task_label": "slicing carrot rounds",
      "start_seconds": 0.0,
      "end_seconds": 40.0,
      "start_timestamp": "00:00:00.000",
      "end_timestamp": "00:00:40.000"
    },
    "source_file": "dataset\\cut_carrot_split\\cut_carrot_night_ir.mp4",
    "annotations": {
      "object_recognition": {
        "caption": "",
        "question": "",
        "answer": ""
      },
      "spatial_reasoning": {
        "caption": "",
        "question": "",
        "answer": ""
      },
      "text_recognition": {
        "caption": "",
        "question": "",
        "answer": ""
      },
      "scene_sequence": {
        "caption": "",
        "question": "",
        "answer": ""
      },
      "light_recongnition": {
        "caption": "",
        "question": "",
        "answer": ""
      },
      "light_change": {
        "caption": "",
        "question": "",
        "answer": ""
      },
      "counting": {
        "caption": "",
        "question": "",
        "answer": ""
      },
      "dynamic_counting": {
        "caption": "",
        "question": "",
        "answer": ""
      },
      "non_common": {
        "caption": "",
        "question": "",
        "answer": ""
      },
      "navigation": {
        "caption": "",
        "question": "",
        "answer": ""
      },
      "dynamic_recognition": {
        "caption": "",
        "question": "",
        "answer": ""
      },
      "action": {
        "caption": "",
        "question": "",
        "answer": ""
      }
    }
  },
  "dataset\\cut_carrot_split\\cut_carrot_night_seg_002": {
    "source_prefix": "cut_carrot_night",
    "side": "night",
    "segment": {
      "segment_id": "cut_carrot_night_seg_002",
      "task_label": "julienning carrots",
      "start_seconds": 40.0,
      "end_seconds": 140.0,
      "start_timestamp": "00:00:40.000",
      "end_timestamp": "00:02:20.000"
    },
    "source_file": "dataset\\cut_carrot_split\\cut_carrot_night_ir.mp4",
    "annotations": {
      "object_recognition": {
        "caption": "",
        "question": "",
        "answer": ""
      },
      "spatial_reasoning": {
        "caption": "",
        "question": "",
        "answer": ""
      },
      "text_recognition": {
        "caption": "",
        "question": "",
        "answer": ""
      },
      "scene_sequence": {
        "caption": "",
        "question": "",
        "answer": ""
      },
      "light_recongnition": {
        "caption": "",
        "question": "",
        "answer": ""
      },
      "light_change": {
        "caption": "",
        "question": "",
        "answer": ""
      },
      "counting": {
        "caption": "",
        "question": "",
        "answer": ""
      },
      "dynamic_counting": {
        "caption": "",
        "question": "",
        "answer": ""
      },
      "non_common": {
        "caption": "",
        "question": "",
        "answer": ""
      },
      "navigation": {
        "caption": "",
        "question": "",
        "answer": ""
      },
      "dynamic_recognition": {
        "caption": "",
        "question": "",
        "answer": ""
      },
      "action": {
        "caption": "",
        "question": "",
        "answer": ""
      }
    }
  },
  "dataset\\cut_carrot_split\\cut_carrot_night_seg_003": {
    "source_prefix": "cut_carrot_night",
    "side": "night",
    "segment": {
      "segment_id": "cut_carrot_night_seg_003",
      "task_label": "gathering julienned carrots",
      "start_seconds": 140.0,
      "end_seconds": 161.933,
      "start_timestamp": "00:02:20.000",
      "end_timestamp": "00:02:41.933"
    },
    "source_file": "dataset\\cut_carrot_split\\cut_carrot_night_ir.mp4",
    "annotations": {
      "object_recognition": {
        "caption": "",
        "question": "",
        "answer": ""
      },
      "spatial_reasoning": {
        "caption": "",
        "question": "",
        "answer": ""
      },
      "text_recognition": {
        "caption": "",
        "question": "",
        "answer": ""
      },
      "scene_sequence": {
        "caption": "",
        "question": "",
        "answer": ""
      },
      "light_recongnition": {
        "caption": "",
        "question": "",
        "answer": ""
      },
      "light_change": {
        "caption": "",
        "question": "",
        "answer": ""
      },
      "counting": {
        "caption": "",
        "question": "",
        "answer": ""
      },
      "dynamic_counting": {
        "caption": "",
        "question": "",
        "answer": ""
      },
      "non_common": {
        "caption": "",
        "question": "",
        "answer": ""
      },
      "navigation": {
        "caption": "",
        "question": "",
        "answer": ""
      },
      "dynamic_recognition": {
        "caption": "",
        "question": "",
        "answer": ""
      },
      "action": {
        "caption": "",
        "question": "",
        "answer": ""
      }
    }
  },
  "dataset\\wash_hand_split\\wash_hands_day_seg_001": {
    "source_prefix": "wash_hands_day",
    "side": "day",
    "segment": {
      "segment_id": "wash_hands_day_seg_001",
      "task_label": "leave room and go to bathroom",
      "start_seconds": 0.0,
      "end_seconds": 38.0,
      "start_timestamp": "00:00:00.000",
      "end_timestamp": "00:00:38.000"
    },
    "source_file": "dataset\\wash_hand_split\\wash_hands_day_ir.mp4",
    "annotations": {
      "object_recognition": {
        "caption": "",
        "question": "",
        "answer": ""
      },
      "spatial_reasoning": {
        "caption": "",
        "question": "",
        "answer": ""
      },
      "text_recognition": {
        "caption": "",
        "question": "",
        "answer": ""
      },
      "scene_sequence": {
        "caption": "",
        "question": "",
        "answer": ""
      },
      "light_recongnition": {
        "caption": "",
        "question": "",
        "answer": ""
      },
      "light_change": {
        "caption": "",
        "question": "",
        "answer": ""
      },
      "counting": {
        "caption": "",
        "question": "",
        "answer": ""
      },
      "dynamic_counting": {
        "caption": "",
        "question": "",
        "answer": ""
      },
      "non_common": {
        "caption": "",
        "question": "",
        "answer": ""
      },
      "navigation": {
        "caption": "",
        "question": "",
        "answer": ""
      },
      "dynamic_recognition": {
        "caption": "",
        "question": "",
        "answer": ""
      },
      "action": {
        "caption": "",
        "question": "",
        "answer": ""
      }
    }
  },
  "dataset\\wash_hand_split\\wash_hands_day_seg_002": {
    "source_prefix": "wash_hands_day",
    "side": "day",
    "segment": {
      "segment_id": "wash_hands_day_seg_002",
      "task_label": "wash hands",
      "start_seconds": 38.0,
      "end_seconds": 81.0,
      "start_timestamp": "00:00:38.000",
      "end_timestamp": "00:01:21.000"
    },
    "source_file": "dataset\\wash_hand_split\\wash_hands_day_ir.mp4",
    "annotations": {
      "object_recognition": {
        "caption": "",
        "question": "",
        "answer": ""
      },
      "spatial_reasoning": {
        "caption": "",
        "question": "",
        "answer": ""
      },
      "text_recognition": {
        "caption": "",
        "question": "",
        "answer": ""
      },
      "scene_sequence": {
        "caption": "",
        "question": "",
        "answer": ""
      },
      "light_recongnition": {
        "caption": "",
        "question": "",
        "answer": ""
      },
      "light_change": {
        "caption": "",
        "question": "",
        "answer": ""
      },
      "counting": {
        "caption": "",
        "question": "",
        "answer": ""
      },
      "dynamic_counting": {
        "caption": "",
        "question": "",
        "answer": ""
      },
      "non_common": {
        "caption": "",
        "question": "",
        "answer": ""
      },
      "navigation": {
        "caption": "",
        "question": "",
        "answer": ""
      },
      "dynamic_recognition": {
        "caption": "",
        "question": "",
        "answer": ""
      },
      "action": {
        "caption": "",
        "question": "",
        "answer": ""
      }
    }
  },
  "dataset\\wash_hand_split\\wash_hands_day_seg_003": {
    "source_prefix": "wash_hands_day",
    "side": "day",
    "segment": {
      "segment_id": "wash_hands_day_seg_003",
      "task_label": "dry hands and return to desk",
      "start_seconds": 81.0,
      "end_seconds": 124.7,
      "start_timestamp": "00:01:21.000",
      "end_timestamp": "00:02:04.700"
    },
    "source_file": "dataset\\wash_hand_split\\wash_hands_day_ir.mp4",
    "annotations": {
      "object_recognition": {
        "caption": "",
        "question": "",
        "answer": ""
      },
      "spatial_reasoning": {
        "caption": "",
        "question": "",
        "answer": ""
      },
      "text_recognition": {
        "caption": "",
        "question": "",
        "answer": ""
      },
      "scene_sequence": {
        "caption": "",
        "question": "",
        "answer": ""
      },
      "light_recongnition": {
        "caption": "",
        "question": "",
        "answer": ""
      },
      "light_change": {
        "caption": "",
        "question": "",
        "answer": ""
      },
      "counting": {
        "caption": "",
        "question": "",
        "answer": ""
      },
      "dynamic_counting": {
        "caption": "",
        "question": "",
        "answer": ""
      },
      "non_common": {
        "caption": "",
        "question": "",
        "answer": ""
      },
      "navigation": {
        "caption": "",
        "question": "",
        "answer": ""
      },
      "dynamic_recognition": {
        "caption": "",
        "question": "",
        "answer": ""
      },
      "action": {
        "caption": "",
        "question": "",
        "answer": ""
      }
    }
  },
  "dataset\\wash_hand_split\\wash_hands_night_seg_001": {
    "source_prefix": "wash_hands_night",
    "side": "night",
    "segment": {
      "segment_id": "wash_hands_night_seg_001",
      "task_label": "walk to bathroom",
      "start_seconds": 0.0,
      "end_seconds": 34.0,
      "start_timestamp": "00:00:00.000",
      "end_timestamp": "00:00:34.000"
    },
    "source_file": "dataset\\wash_hand_split\\wash_hands_night_ir.mp4",
    "annotations": {
      "object_recognition": {
        "caption": "The infrared video shows an office setting featuring multiple computer monitors with significant thermal signatures, appearing as bright rectangular hotspots on dark desk surfaces. Large windows reveal a building across the street with distinct heat-emitting windows. As the subject moves, a doorway leads into a hallway with a light-colored wooden floor. A square ceiling light fixture provides a localized high-intensity thermal signature.",
        "question": "What items are on the desks that exhibit the highest thermal contrast?",
        "answer": "Computer monitors"
      },
      "spatial_reasoning": {
        "caption": "In the initial scene, several computer monitors are positioned on desks, approximately 2 steps from each other. The desks are located next to a large window, about 1 step away. As I move toward the doorway, the entrance is roughly 5 steps from the starting position. Upon entering the hallway, a square ceiling light is positioned directly above, while the hallway floor extends approximately 10 steps ahead.",
        "question": "What is the spatial relationship between the computer monitors and the desks they sit on?",
        "answer": "On top"
      },
      "text_recognition": {
        "caption": "At frame 000210, the center computer monitor displays a faint, bright horizontal line-like pattern, possibly a cursor or a simple UI element. At frame 000690, the square ceiling light fixture shows a grid-like pattern of four horizontal segments, which is likely part of its internal heat distribution or casing design.",
        "question": "In which frame do I observe a horizontal line-like pattern on the monitor screen?",
        "answer": "Frame 000210"
      },
      "scene_sequence": {
        "caption": "The video sequence begins in a dimly lit office with several workstations. I then move through the office towards a doorway, entering a brightly reflected hallway with wooden floors. While in the hallway, I look directly up at a square ceiling light fixture. Finally, I turn around and navigate back through the same doorway to return to the original office workspace.",
        "question": "What is the sequence of scenes I just passed?",
        "answer": "Office, hallway, office"
      },
      "light_recongnition": {
        "caption": "The primary light sources identified are the emissive computer screens in the office and a prominent square ceiling light in the hallway. Outside the office window, smaller point-like light sources from streetlights or adjacent building windows are visible. The ceiling light is the strongest source, directed downwards, appearing as a bright white square in the IR spectrum.",
        "question": "What is the shape of the main light source in the hallway?",
        "answer": "Square"
      },
      "light_change": {
        "caption": "The video starts with low ambient light in the office, where only monitors provide illumination. There is a significant increase in brightness when I move into the hallway due to reflections on the floor. A sudden surge in thermal intensity occurs when I look up at the ceiling light, which then subsides as I lower my gaze and eventually return to the darker office environment.",
        "question": "Did the light get brighter or darker when I moved into the hallway?",
        "answer": "Brighter"
      },
      "counting": {
        "caption": "Throughout the video, I can identify approximately 4 computer monitors, 3 desks, 2 large windows, 1 doorway, and 1 main ceiling light fixture. The hallway features a continuous wooden floor surface.",
        "question": "How many computer monitors did I pass in the office?",
        "answer": "Four"
      },
      "dynamic_counting": {
        "caption": "Analysis of the video frames shows a static environment. There are no moving objects, cars outside the window, or other individuals present in the office or hallway during the entire duration of the recording.",
        "question": "How many other people are walking in the hallway?",
        "answer": "Zero"
      },
      "non_common": {
        "caption": "In the hallway scene, the ceiling light fixture appears somewhat detached from the ceiling surface in frame 000720, resembling a floating 2D plane rather than a 3D recessed or mounted light, which is a common visual artifact in simulated environments.",
        "question": "What object in the hallway appears to be floating unnaturally?",
        "answer": "Ceiling light"
      },
      "navigation": {
        "caption": "Starting in the office, I walk forward about 5 steps to reach the doorway. I then turn slightly left and enter the hallway, walking another 3 steps. I stop and look up, then turn 180 degrees and walk back 8 steps through the door and into the initial office area.",
        "question": "How many steps did I take to reach the doorway from the office start?",
        "answer": "Five steps"
      },
      "dynamic_recognition": {
        "caption": "No dynamic objects or humans other than the subject behind the camera are identified in this video. The scene remains completely static from frame 000000 to frame 000990.",
        "question": "Did any cars pass by the window while I was in the office?",
        "answer": "No"
      },
      "action": {
        "caption": "I am exploring an office environment. My actions include scanning the workspace with the camera, walking toward a hallway, looking upward to inspect a ceiling light fixture, and then retracing my steps to return to the original room. The purpose seems to be a general inspection or navigation through the space.",
        "question": "What did I do after looking up at the ceiling light?",
        "answer": "Returned to office"
      }
    }
  },
  "dataset\\wash_hand_split\\wash_hands_night_seg_002": {
    "source_prefix": "wash_hands_night",
    "side": "night",
    "segment": {
      "segment_id": "wash_hands_night_seg_002",
      "task_label": "wash hands",
      "start_seconds": 34.0,
      "end_seconds": 86.0,
      "start_timestamp": "00:00:34.000",
      "end_timestamp": "00:01:26.000"
    },
    "source_file": "dataset\\wash_hand_split\\wash_hands_night_ir.mp4",
    "annotations": {
      "object_recognition": {
        "caption": "",
        "question": "",
        "answer": ""
      },
      "spatial_reasoning": {
        "caption": "",
        "question": "",
        "answer": ""
      },
      "text_recognition": {
        "caption": "",
        "question": "",
        "answer": ""
      },
      "scene_sequence": {
        "caption": "",
        "question": "",
        "answer": ""
      },
      "light_recongnition": {
        "caption": "",
        "question": "",
        "answer": ""
      },
      "light_change": {
        "caption": "",
        "question": "",
        "answer": ""
      },
      "counting": {
        "caption": "",
        "question": "",
        "answer": ""
      },
      "dynamic_counting": {
        "caption": "",
        "question": "",
        "answer": ""
      },
      "non_common": {
        "caption": "",
        "question": "",
        "answer": ""
      },
      "navigation": {
        "caption": "",
        "question": "",
        "answer": ""
      },
      "dynamic_recognition": {
        "caption": "",
        "question": "",
        "answer": ""
      },
      "action": {
        "caption": "",
        "question": "",
        "answer": ""
      }
    }
  },
  "dataset\\wash_hand_split\\wash_hands_night_seg_003": {
    "source_prefix": "wash_hands_night",
    "side": "night",
    "segment": {
      "segment_id": "wash_hands_night_seg_003",
      "task_label": "dry hands and return",
      "start_seconds": 86.0,
      "end_seconds": 138.5,
      "start_timestamp": "00:01:26.000",
      "end_timestamp": "00:02:18.500"
    },
    "source_file": "dataset\\wash_hand_split\\wash_hands_night_ir.mp4",
    "annotations": {
      "object_recognition": {
        "caption": "",
        "question": "",
        "answer": ""
      },
      "spatial_reasoning": {
        "caption": "",
        "question": "",
        "answer": ""
      },
      "text_recognition": {
        "caption": "",
        "question": "",
        "answer": ""
      },
      "scene_sequence": {
        "caption": "",
        "question": "",
        "answer": ""
      },
      "light_recongnition": {
        "caption": "",
        "question": "",
        "answer": ""
      },
      "light_change": {
        "caption": "",
        "question": "",
        "answer": ""
      },
      "counting": {
        "caption": "",
        "question": "",
        "answer": ""
      },
      "dynamic_counting": {
        "caption": "",
        "question": "",
        "answer": ""
      },
      "non_common": {
        "caption": "",
        "question": "",
        "answer": ""
      },
      "navigation": {
        "caption": "",
        "question": "",
        "answer": ""
      },
      "dynamic_recognition": {
        "caption": "",
        "question": "",
        "answer": ""
      },
      "action": {
        "caption": "",
        "question": "",
        "answer": ""
      }
    }
  }
}